[
    {
        "id": "mordern-city-sidewalk-at-night",
        "title": "Modern city sidewalk at night",
        "promptFile": "prompts/mordern-city-sidewalk-at-night.txt",
        "imageUrl": "images/optimized/mordern-city-sidewalk-at-night.webp"
    },
    {
        "id": "sit-on-rusty-jeep",
        "title": "Sit on rusty jeep in the forest",
        "promptFile": "prompts/sit-on-rusty-jeep.txt",
        "imageUrl": "images/optimized/sit-on-rusty-jeep.webp"
    },
    {
        "id": "brown-jacket-outdoor",
        "title": "Brown jacket outdoor",
        "promptFile": "prompts/brown-jacket-outdoor.txt",
        "imageUrl": "images/optimized/brown-jacket-outdoor.webp"
    },
    {
        "id": "urban-night-streetwear-editorial",
        "title": "Urban Night Streetwear Editorial",
        "promptFile": "prompts/urban-night-streetwear-editorial.txt",
        "imageUrl": "images/optimized/urban-night-streetwear-editorial.webp"
    }
]